[
    {
        "name": "Mount Arab",
        "coordinates": [
            -74.58853,
            44.2046262
        ],
        "elevation": null,
        "type": "viewpoints",
        "source": "Viewpoints"
    },
    {
        "name": "Indian Falls Lookout",
        "coordinates": [
            -73.9292171,
            44.1405071
        ],
        "elevation": null,
        "type": "viewpoints",
        "source": "Viewpoints"
    },
    {
        "name": "No name",
        "coordinates": [
            -73.5067209,
            44.4004678
        ],
        "elevation": null,
        "type": "viewpoints",
        "source": "Viewpoints"
    },
    {
        "name": "No name",
        "coordinates": [
            -73.5156853,
            44.4010406
        ],
        "elevation": null,
        "type": "viewpoints",
        "source": "Viewpoints"
    },
    {
        "name": "Wanika Falls",
        "coordinates": [
            -74.055717,
            44.1986092
        ],
        "elevation": null,
        "type": "viewpoints",
        "source": "Viewpoints"
    },
    {
        "name": "No name",
        "coordinates": [
            -74.2605921,
            44.4335961
        ],
        "elevation": null,
        "type": "viewpoints",
        "source": "Viewpoints"
    },
    {
        "name": "No name",
        "coordinates": [
            -73.6713122,
            44.1573294
        ],
        "elevation": null,
        "type": "viewpoints",
        "source": "Viewpoints"
    },
    {
        "name": "No name",
        "coordinates": [
            -74.0390129,
            44.3310339
        ],
        "elevation": null,
        "type": "viewpoints",
        "source": "Viewpoints"
    },
    {
        "name": "No name",
        "coordinates": [
            -74.0335315,
            44.3351388
        ],
        "elevation": null,
        "type": "viewpoints",
        "source": "Viewpoints"
    },
    {
        "name": "No name",
        "coordinates": [
            -74.0322541,
            44.3361415
        ],
        "elevation": null,
        "type": "viewpoints",
        "source": "Viewpoints"
    },
    {
        "name": "No name",
        "coordinates": [
            -74.0325745,
            44.3362543
        ],
        "elevation": null,
        "type": "viewpoints",
        "source": "Viewpoints"
    },
    {
        "name": "No name",
        "coordinates": [
            -74.3307484,
            44.4087794
        ],
        "elevation": null,
        "type": "viewpoints",
        "source": "Viewpoints"
    },
    {
        "name": "No name",
        "coordinates": [
            -73.8564315,
            44.211956
        ],
        "elevation": null,
        "type": "viewpoints",
        "source": "Viewpoints"
    },
    {
        "name": "No name",
        "coordinates": [
            -73.9727204,
            44.1155011
        ],
        "elevation": null,
        "type": "viewpoints",
        "source": "Viewpoints"
    },
    {
        "name": "No name",
        "coordinates": [
            -73.9724613,
            44.1150284
        ],
        "elevation": null,
        "type": "viewpoints",
        "source": "Viewpoints"
    },
    {
        "name": "No name",
        "coordinates": [
            -73.9362629,
            44.1111584
        ],
        "elevation": null,
        "type": "viewpoints",
        "source": "Viewpoints"
    },
    {
        "name": "Great Slide Lookout",
        "coordinates": [
            -73.7569187,
            44.0664198
        ],
        "elevation": null,
        "type": "viewpoints",
        "source": "Viewpoints"
    },
    {
        "name": "Allen Lookout North",
        "coordinates": [
            -73.9397822,
            44.0709706
        ],
        "elevation": null,
        "type": "viewpoints",
        "source": "Viewpoints"
    },
    {
        "name": "Roger's Lookout",
        "coordinates": [
            -73.9673623,
            44.1840536
        ],
        "elevation": null,
        "type": "viewpoints",
        "source": "Viewpoints"
    },
    {
        "name": "MacIntyre Falls Lookout",
        "coordinates": [
            -73.9795851,
            44.1593353
        ],
        "elevation": null,
        "type": "viewpoints",
        "source": "Viewpoints"
    },
    {
        "name": "Summit Rock",
        "coordinates": [
            -74.0333908,
            44.135277
        ],
        "elevation": null,
        "type": "viewpoints",
        "source": "Viewpoints"
    },
    {
        "name": "No name",
        "coordinates": [
            -73.8891154,
            44.1182607
        ],
        "elevation": null,
        "type": "viewpoints",
        "source": "Viewpoints"
    },
    {
        "name": "No name",
        "coordinates": [
            -73.8864963,
            44.1215362
        ],
        "elevation": null,
        "type": "viewpoints",
        "source": "Viewpoints"
    },
    {
        "name": "No name",
        "coordinates": [
            -73.87382,
            44.1257404
        ],
        "elevation": null,
        "type": "viewpoints",
        "source": "Viewpoints"
    },
    {
        "name": "No name",
        "coordinates": [
            -74.1306929,
            44.0831775
        ],
        "elevation": null,
        "type": "viewpoints",
        "source": "Viewpoints"
    },
    {
        "name": "No name",
        "coordinates": [
            -74.0822236,
            44.2685301
        ],
        "elevation": null,
        "type": "viewpoints",
        "source": "Viewpoints"
    },
    {
        "name": "No name",
        "coordinates": [
            -74.0559523,
            44.3197985
        ],
        "elevation": null,
        "type": "viewpoints",
        "source": "Viewpoints"
    },
    {
        "name": "No name",
        "coordinates": [
            -74.0543585,
            44.3205611
        ],
        "elevation": null,
        "type": "viewpoints",
        "source": "Viewpoints"
    },
    {
        "name": "No name",
        "coordinates": [
            -74.2629212,
            44.4484281
        ],
        "elevation": null,
        "type": "viewpoints",
        "source": "Viewpoints"
    },
    {
        "name": "No name",
        "coordinates": [
            -74.2645144,
            44.4484166
        ],
        "elevation": null,
        "type": "viewpoints",
        "source": "Viewpoints"
    },
    {
        "name": "No name",
        "coordinates": [
            -74.2591768,
            44.4455559
        ],
        "elevation": null,
        "type": "viewpoints",
        "source": "Viewpoints"
    },
    {
        "name": "No name",
        "coordinates": [
            -73.8634725,
            44.3841273
        ],
        "elevation": null,
        "type": "viewpoints",
        "source": "Viewpoints"
    },
    {
        "name": "No name",
        "coordinates": [
            -73.887253,
            44.3781025
        ],
        "elevation": null,
        "type": "viewpoints",
        "source": "Viewpoints"
    },
    {
        "name": "Hitch-up Matilda",
        "coordinates": [
            -73.9676899,
            44.1332845
        ],
        "elevation": null,
        "type": "viewpoints",
        "source": "Viewpoints"
    },
    {
        "name": "Hitch-up Matilda",
        "coordinates": [
            -73.9687588,
            44.1324672
        ],
        "elevation": null,
        "type": "viewpoints",
        "source": "Viewpoints"
    },
    {
        "name": "No name",
        "coordinates": [
            -74.0108568,
            44.1274266
        ],
        "elevation": null,
        "type": "viewpoints",
        "source": "Viewpoints"
    },
    {
        "name": "No name",
        "coordinates": [
            -74.0112578,
            44.1275038
        ],
        "elevation": null,
        "type": "viewpoints",
        "source": "Viewpoints"
    },
    {
        "name": "No name",
        "coordinates": [
            -73.8348209,
            44.0938436
        ],
        "elevation": null,
        "type": "viewpoints",
        "source": "Viewpoints"
    },
    {
        "name": "South Dix Lookout",
        "coordinates": [
            -73.7723998,
            44.0604244
        ],
        "elevation": null,
        "type": "viewpoints",
        "source": "Viewpoints"
    },
    {
        "name": "Ridge Lookout",
        "coordinates": [
            -73.7390968,
            44.1406303
        ],
        "elevation": null,
        "type": "viewpoints",
        "source": "Viewpoints"
    },
    {
        "name": "Giant East Slide Lookout",
        "coordinates": [
            -73.7166793,
            44.1591851
        ],
        "elevation": null,
        "type": "viewpoints",
        "source": "Viewpoints"
    },
    {
        "name": "No name",
        "coordinates": [
            -74.2004307,
            44.1594176
        ],
        "elevation": null,
        "type": "viewpoints",
        "source": "Viewpoints"
    },
    {
        "name": "No name",
        "coordinates": [
            -74.2147599,
            44.1470555
        ],
        "elevation": null,
        "type": "viewpoints",
        "source": "Viewpoints"
    },
    {
        "name": "No name",
        "coordinates": [
            -74.211214,
            44.1546501
        ],
        "elevation": null,
        "type": "viewpoints",
        "source": "Viewpoints"
    },
    {
        "name": "No name",
        "coordinates": [
            -74.0238923,
            44.1866897
        ],
        "elevation": null,
        "type": "viewpoints",
        "source": "Viewpoints"
    },
    {
        "name": "No name",
        "coordinates": [
            -74.0236976,
            44.1872607
        ],
        "elevation": null,
        "type": "viewpoints",
        "source": "Viewpoints"
    },
    {
        "name": "No name",
        "coordinates": [
            -74.0271053,
            44.1792781
        ],
        "elevation": null,
        "type": "viewpoints",
        "source": "Viewpoints"
    },
    {
        "name": "No name",
        "coordinates": [
            -73.9312615,
            44.2102202
        ],
        "elevation": null,
        "type": "viewpoints",
        "source": "Viewpoints"
    },
    {
        "name": "No name",
        "coordinates": [
            -73.7869689,
            44.1250007
        ],
        "elevation": null,
        "type": "viewpoints",
        "source": "Viewpoints"
    },
    {
        "name": "Big Slide Lookout",
        "coordinates": [
            -73.8704589,
            44.1823266
        ],
        "elevation": null,
        "type": "viewpoints",
        "source": "Viewpoints"
    },
    {
        "name": "No name",
        "coordinates": [
            -73.8516053,
            44.1869985
        ],
        "elevation": null,
        "type": "viewpoints",
        "source": "Viewpoints"
    },
    {
        "name": "No name",
        "coordinates": [
            -74.1728633,
            44.1582244
        ],
        "elevation": null,
        "type": "viewpoints",
        "source": "Viewpoints"
    },
    {
        "name": "Jay Mountain Lookout",
        "coordinates": [
            -73.6900652,
            44.3156454
        ],
        "elevation": null,
        "type": "viewpoints",
        "source": "Viewpoints"
    },
    {
        "name": "Wedge Brook Cascades Lookout",
        "coordinates": [
            -73.8112709,
            44.1360789
        ],
        "elevation": null,
        "type": "viewpoints",
        "source": "Viewpoints"
    },
    {
        "name": "Valley View Ledge",
        "coordinates": [
            -73.8079527,
            44.1758152
        ],
        "elevation": null,
        "type": "viewpoints",
        "source": "Viewpoints"
    },
    {
        "name": "Snow Mountain Lookout",
        "coordinates": [
            -73.7944186,
            44.1677691
        ],
        "elevation": null,
        "type": "viewpoints",
        "source": "Viewpoints"
    },
    {
        "name": "Marble Point",
        "coordinates": [
            -73.8440173,
            44.1070796
        ],
        "elevation": null,
        "type": "viewpoints",
        "source": "Viewpoints"
    },
    {
        "name": "Outlook #2",
        "coordinates": [
            -73.8327398,
            44.1086641
        ],
        "elevation": null,
        "type": "viewpoints",
        "source": "Viewpoints"
    },
    {
        "name": "Outlook #1",
        "coordinates": [
            -73.8323205,
            44.1084548
        ],
        "elevation": null,
        "type": "viewpoints",
        "source": "Viewpoints"
    },
    {
        "name": "Outlook #4",
        "coordinates": [
            -73.8372277,
            44.1104884
        ],
        "elevation": null,
        "type": "viewpoints",
        "source": "Viewpoints"
    },
    {
        "name": "Outlook #5",
        "coordinates": [
            -73.8441922,
            44.1106473
        ],
        "elevation": null,
        "type": "viewpoints",
        "source": "Viewpoints"
    },
    {
        "name": "Outlook #3",
        "coordinates": [
            -73.8355217,
            44.1094652
        ],
        "elevation": null,
        "type": "viewpoints",
        "source": "Viewpoints"
    },
    {
        "name": "Rainbows Falls Lookout",
        "coordinates": [
            -73.8296714,
            44.1180002
        ],
        "elevation": null,
        "type": "viewpoints",
        "source": "Viewpoints"
    },
    {
        "name": "Allen Lookout East",
        "coordinates": [
            -73.9397076,
            44.0707489
        ],
        "elevation": null,
        "type": "viewpoints",
        "source": "Viewpoints"
    },
    {
        "name": "Gothic Window",
        "coordinates": [
            -73.8234978,
            44.1152514
        ],
        "elevation": null,
        "type": "viewpoints",
        "source": "Viewpoints"
    },
    {
        "name": "South Outlook",
        "coordinates": [
            -73.8237241,
            44.1120974
        ],
        "elevation": null,
        "type": "viewpoints",
        "source": "Viewpoints"
    },
    {
        "name": "North Outlook",
        "coordinates": [
            -73.8189991,
            44.1148924
        ],
        "elevation": null,
        "type": "viewpoints",
        "source": "Viewpoints"
    },
    {
        "name": "Pyramid Peak Lookout",
        "coordinates": [
            -73.85625,
            44.1235942
        ],
        "elevation": null,
        "type": "viewpoints",
        "source": "Viewpoints"
    },
    {
        "name": "High Bank",
        "coordinates": [
            -73.6896345,
            44.1737035
        ],
        "elevation": null,
        "type": "viewpoints",
        "source": "Viewpoints"
    },
    {
        "name": "Roaring Brook Falls Lower Lookout",
        "coordinates": [
            -73.7611301,
            44.1503463
        ],
        "elevation": null,
        "type": "viewpoints",
        "source": "Viewpoints"
    },
    {
        "name": "Roaring Brook Falls Upper Lookout",
        "coordinates": [
            -73.7600438,
            44.1506792
        ],
        "elevation": null,
        "type": "viewpoints",
        "source": "Viewpoints"
    },
    {
        "name": "Sawteeth Lookout",
        "coordinates": [
            -73.8508031,
            44.113679
        ],
        "elevation": null,
        "type": "viewpoints",
        "source": "Viewpoints"
    },
    {
        "name": "Blueberry Cobbles",
        "coordinates": [
            -73.6494202,
            44.1506735
        ],
        "elevation": null,
        "type": "viewpoints",
        "source": "Viewpoints"
    },
    {
        "name": "Fish Hawk Cliffs Lookout",
        "coordinates": [
            -73.8244149,
            44.110022
        ],
        "elevation": null,
        "type": "viewpoints",
        "source": "Viewpoints"
    },
    {
        "name": "No name",
        "coordinates": [
            -73.7742475,
            44.0598451
        ],
        "elevation": null,
        "type": "viewpoints",
        "source": "Viewpoints"
    },
    {
        "name": "No name",
        "coordinates": [
            -73.7768331,
            44.0631906
        ],
        "elevation": null,
        "type": "viewpoints",
        "source": "Viewpoints"
    },
    {
        "name": "No name",
        "coordinates": [
            -73.7788649,
            44.0680474
        ],
        "elevation": null,
        "type": "viewpoints",
        "source": "Viewpoints"
    },
    {
        "name": "No name",
        "coordinates": [
            -73.7791546,
            44.0759879
        ],
        "elevation": null,
        "type": "viewpoints",
        "source": "Viewpoints"
    },
    {
        "name": "No name",
        "coordinates": [
            -73.7817784,
            44.0785246
        ],
        "elevation": null,
        "type": "viewpoints",
        "source": "Viewpoints"
    },
    {
        "name": "No name",
        "coordinates": [
            -73.7800913,
            44.0779408
        ],
        "elevation": null,
        "type": "viewpoints",
        "source": "Viewpoints"
    },
    {
        "name": "Yard Lookout",
        "coordinates": [
            -73.8852657,
            44.174115
        ],
        "elevation": null,
        "type": "viewpoints",
        "source": "Viewpoints"
    },
    {
        "name": "Big Slide Lookout West",
        "coordinates": [
            -73.8749928,
            44.1810081
        ],
        "elevation": null,
        "type": "viewpoints",
        "source": "Viewpoints"
    },
    {
        "name": "72 Steps",
        "coordinates": [
            -73.8525439,
            44.0702626
        ],
        "elevation": null,
        "type": "viewpoints",
        "source": "Viewpoints"
    },
    {
        "name": "Lookout Rock",
        "coordinates": [
            -73.8468093,
            44.0775275
        ],
        "elevation": null,
        "type": "viewpoints",
        "source": "Viewpoints"
    },
    {
        "name": "No name",
        "coordinates": [
            -73.8285863,
            44.1186293
        ],
        "elevation": null,
        "type": "viewpoints",
        "source": "Viewpoints"
    },
    {
        "name": "No name",
        "coordinates": [
            -73.8229457,
            44.1271782
        ],
        "elevation": null,
        "type": "viewpoints",
        "source": "Viewpoints"
    },
    {
        "name": "No name",
        "coordinates": [
            -73.8242331,
            44.1263465
        ],
        "elevation": null,
        "type": "viewpoints",
        "source": "Viewpoints"
    },
    {
        "name": "No name",
        "coordinates": [
            -73.7341735,
            44.4185722
        ],
        "elevation": null,
        "type": "viewpoints",
        "source": "Viewpoints"
    },
    {
        "name": "No name",
        "coordinates": [
            -73.7374269,
            44.4179562
        ],
        "elevation": null,
        "type": "viewpoints",
        "source": "Viewpoints"
    },
    {
        "name": "No name",
        "coordinates": [
            -73.7357901,
            44.4195435
        ],
        "elevation": null,
        "type": "viewpoints",
        "source": "Viewpoints"
    },
    {
        "name": "No name",
        "coordinates": [
            -73.7607419,
            44.2155363
        ],
        "elevation": null,
        "type": "viewpoints",
        "source": "Viewpoints"
    },
    {
        "name": "No name",
        "coordinates": [
            -73.7621816,
            44.1744047
        ],
        "elevation": null,
        "type": "viewpoints",
        "source": "Viewpoints"
    },
    {
        "name": "No name",
        "coordinates": [
            -73.7568238,
            44.1868259
        ],
        "elevation": null,
        "type": "viewpoints",
        "source": "Viewpoints"
    },
    {
        "name": "No name",
        "coordinates": [
            -73.7595731,
            44.1884069
        ],
        "elevation": null,
        "type": "viewpoints",
        "source": "Viewpoints"
    },
    {
        "name": "No name",
        "coordinates": [
            -73.7446828,
            44.1468075
        ],
        "elevation": null,
        "type": "viewpoints",
        "source": "Viewpoints"
    },
    {
        "name": "No name",
        "coordinates": [
            -73.7434411,
            44.1460352
        ],
        "elevation": null,
        "type": "viewpoints",
        "source": "Viewpoints"
    },
    {
        "name": "No name",
        "coordinates": [
            -73.6428541,
            44.1529309
        ],
        "elevation": null,
        "type": "viewpoints",
        "source": "Viewpoints"
    },
    {
        "name": "No name",
        "coordinates": [
            -74.104076,
            44.3342934
        ],
        "elevation": null,
        "type": "viewpoints",
        "source": "Viewpoints"
    },
    {
        "name": "No name",
        "coordinates": [
            -73.9029995,
            44.365763
        ],
        "elevation": null,
        "type": "viewpoints",
        "source": "Viewpoints"
    },
    {
        "name": "No name",
        "coordinates": [
            -73.9030498,
            44.3658387
        ],
        "elevation": null,
        "type": "viewpoints",
        "source": "Viewpoints"
    },
    {
        "name": "No name",
        "coordinates": [
            -73.6407075,
            44.2336719
        ],
        "elevation": null,
        "type": "viewpoints",
        "source": "Viewpoints"
    },
    {
        "name": "No name",
        "coordinates": [
            -74.0373487,
            44.3328938
        ],
        "elevation": null,
        "type": "viewpoints",
        "source": "Viewpoints"
    },
    {
        "name": "No name",
        "coordinates": [
            -73.8587998,
            44.4044839
        ],
        "elevation": null,
        "type": "viewpoints",
        "source": "Viewpoints"
    },
    {
        "name": "No name",
        "coordinates": [
            -73.6240072,
            44.1360593
        ],
        "elevation": null,
        "type": "viewpoints",
        "source": "Viewpoints"
    },
    {
        "name": "No name",
        "coordinates": [
            -73.627878,
            44.1347291
        ],
        "elevation": null,
        "type": "viewpoints",
        "source": "Viewpoints"
    },
    {
        "name": "No name",
        "coordinates": [
            -73.6361892,
            44.1354546
        ],
        "elevation": null,
        "type": "viewpoints",
        "source": "Viewpoints"
    },
    {
        "name": "Southwest Corner Lookout",
        "coordinates": [
            -73.9752217,
            44.1750209
        ],
        "elevation": "853",
        "type": "viewpoints",
        "source": "Viewpoints"
    },
    {
        "name": "No name",
        "coordinates": [
            -73.6443052,
            44.1543195
        ],
        "elevation": null,
        "type": "viewpoints",
        "source": "Viewpoints"
    },
    {
        "name": "No name",
        "coordinates": [
            -73.8745549,
            44.3484749
        ],
        "elevation": null,
        "type": "viewpoints",
        "source": "Viewpoints"
    },
    {
        "name": "No name",
        "coordinates": [
            -73.8744141,
            44.348706
        ],
        "elevation": null,
        "type": "viewpoints",
        "source": "Viewpoints"
    },
    {
        "name": "No name",
        "coordinates": [
            -73.8737918,
            44.3490282
        ],
        "elevation": null,
        "type": "viewpoints",
        "source": "Viewpoints"
    },
    {
        "name": "No name",
        "coordinates": [
            -73.8741352,
            44.3487098
        ],
        "elevation": null,
        "type": "viewpoints",
        "source": "Viewpoints"
    },
    {
        "name": "No name",
        "coordinates": [
            -73.8736416,
            44.3490839
        ],
        "elevation": null,
        "type": "viewpoints",
        "source": "Viewpoints"
    },
    {
        "name": "No name",
        "coordinates": [
            -73.8648746,
            44.215483
        ],
        "elevation": null,
        "type": "viewpoints",
        "source": "Viewpoints"
    },
    {
        "name": "No name",
        "coordinates": [
            -73.8925283,
            44.3561627
        ],
        "elevation": null,
        "type": "viewpoints",
        "source": "Viewpoints"
    },
    {
        "name": "west view",
        "coordinates": [
            -73.6134578,
            44.0400338
        ],
        "elevation": null,
        "type": "viewpoints",
        "source": "Viewpoints"
    },
    {
        "name": "south view",
        "coordinates": [
            -73.5977793,
            44.0380581
        ],
        "elevation": null,
        "type": "viewpoints",
        "source": "Viewpoints"
    },
    {
        "name": "Giant Washbowl Overlook",
        "coordinates": [
            -73.741256,
            44.1457748
        ],
        "elevation": null,
        "type": "viewpoints",
        "source": "Viewpoints"
    },
    {
        "name": "Lake Placid Olympic Jumping Complex K-120 Meter Jump Observation Deck",
        "coordinates": [
            -73.967088,
            44.254843
        ],
        "elevation": null,
        "type": "viewpoints",
        "source": "Viewpoints"
    },
    {
        "name": "No name",
        "coordinates": [
            -74.2524689,
            44.4314337
        ],
        "elevation": null,
        "type": "viewpoints",
        "source": "Viewpoints"
    },
    {
        "name": "No name",
        "coordinates": [
            -74.2510581,
            44.4315831
        ],
        "elevation": null,
        "type": "viewpoints",
        "source": "Viewpoints"
    },
    {
        "name": "No name",
        "coordinates": [
            -74.2611179,
            44.4350673
        ],
        "elevation": null,
        "type": "viewpoints",
        "source": "Viewpoints"
    },
    {
        "name": "Giant Mountain",
        "coordinates": [
            -73.7202539,
            44.161092
        ],
        "elevation": null,
        "type": "viewpoints",
        "source": "Viewpoints"
    },
    {
        "name": "California Overlook",
        "coordinates": [
            -73.5966292,
            44.1925791
        ],
        "elevation": null,
        "type": "viewpoints",
        "source": "Viewpoints"
    },
    {
        "name": "Giant View",
        "coordinates": [
            -73.6254078,
            44.2219934
        ],
        "elevation": null,
        "type": "viewpoints",
        "source": "Viewpoints"
    },
    {
        "name": "No name",
        "coordinates": [
            -73.622882,
            44.2204867
        ],
        "elevation": null,
        "type": "viewpoints",
        "source": "Viewpoints"
    },
    {
        "name": "No name",
        "coordinates": [
            -73.6187884,
            44.2272179
        ],
        "elevation": null,
        "type": "viewpoints",
        "source": "Viewpoints"
    },
    {
        "name": "No name",
        "coordinates": [
            -73.643904,
            44.2369414
        ],
        "elevation": null,
        "type": "viewpoints",
        "source": "Viewpoints"
    },
    {
        "name": "No name",
        "coordinates": [
            -73.7679056,
            44.2167876
        ],
        "elevation": null,
        "type": "viewpoints",
        "source": "Viewpoints"
    },
    {
        "name": "No name",
        "coordinates": [
            -73.9308833,
            44.2098742
        ],
        "elevation": null,
        "type": "viewpoints",
        "source": "Viewpoints"
    },
    {
        "name": "No name",
        "coordinates": [
            -73.9304038,
            44.2095546
        ],
        "elevation": null,
        "type": "viewpoints",
        "source": "Viewpoints"
    },
    {
        "name": "No name",
        "coordinates": [
            -73.6923661,
            44.1246258
        ],
        "elevation": null,
        "type": "viewpoints",
        "source": "Viewpoints"
    },
    {
        "name": "No name",
        "coordinates": [
            -73.6918805,
            44.1252829
        ],
        "elevation": null,
        "type": "viewpoints",
        "source": "Viewpoints"
    },
    {
        "name": "No name",
        "coordinates": [
            -74.5449846,
            44.1284203
        ],
        "elevation": null,
        "type": "viewpoints",
        "source": "Viewpoints"
    },
    {
        "name": "No name",
        "coordinates": [
            -74.5452697,
            44.1289054
        ],
        "elevation": null,
        "type": "viewpoints",
        "source": "Viewpoints"
    },
    {
        "name": "No name",
        "coordinates": [
            -73.7816275,
            44.3067956
        ],
        "elevation": null,
        "type": "viewpoints",
        "source": "Viewpoints"
    },
    {
        "name": "No name",
        "coordinates": [
            -74.4500524,
            44.3269006
        ],
        "elevation": null,
        "type": "viewpoints",
        "source": "Viewpoints"
    },
    {
        "name": "No name",
        "coordinates": [
            -74.4497917,
            44.3279974
        ],
        "elevation": null,
        "type": "viewpoints",
        "source": "Viewpoints"
    },
    {
        "name": "No name",
        "coordinates": [
            -73.8133037,
            44.3123645
        ],
        "elevation": null,
        "type": "viewpoints",
        "source": "Viewpoints"
    },
    {
        "name": "No name",
        "coordinates": [
            -73.8134401,
            44.3126953
        ],
        "elevation": null,
        "type": "viewpoints",
        "source": "Viewpoints"
    },
    {
        "name": "No name",
        "coordinates": [
            -73.8123898,
            44.3121496
        ],
        "elevation": null,
        "type": "viewpoints",
        "source": "Viewpoints"
    },
    {
        "name": "No name",
        "coordinates": [
            -73.5672387,
            44.0730725
        ],
        "elevation": null,
        "type": "viewpoints",
        "source": "Viewpoints"
    },
    {
        "name": "No name",
        "coordinates": [
            -73.5838731,
            44.0493144
        ],
        "elevation": null,
        "type": "viewpoints",
        "source": "Viewpoints"
    },
    {
        "name": "No name",
        "coordinates": [
            -73.7336464,
            44.411413
        ],
        "elevation": null,
        "type": "viewpoints",
        "source": "Viewpoints"
    },
    {
        "name": "No name",
        "coordinates": [
            -73.7734588,
            44.3066244
        ],
        "elevation": null,
        "type": "viewpoints",
        "source": "Viewpoints"
    },
    {
        "name": "No name",
        "coordinates": [
            -73.7697732,
            44.2726022
        ],
        "elevation": null,
        "type": "viewpoints",
        "source": "Viewpoints"
    },
    {
        "name": "No name",
        "coordinates": [
            -73.7711894,
            44.2730324
        ],
        "elevation": null,
        "type": "viewpoints",
        "source": "Viewpoints"
    },
    {
        "name": "No name",
        "coordinates": [
            -74.3583187,
            44.0224982
        ],
        "elevation": null,
        "type": "viewpoints",
        "source": "Viewpoints"
    },
    {
        "name": "No name",
        "coordinates": [
            -74.3556043,
            44.0205745
        ],
        "elevation": null,
        "type": "viewpoints",
        "source": "Viewpoints"
    },
    {
        "name": "No name",
        "coordinates": [
            -73.5702784,
            44.0227926
        ],
        "elevation": null,
        "type": "viewpoints",
        "source": "Viewpoints"
    },
    {
        "name": "No name",
        "coordinates": [
            -73.7288536,
            44.1210716
        ],
        "elevation": null,
        "type": "viewpoints",
        "source": "Viewpoints"
    },
    {
        "name": "No name",
        "coordinates": [
            -73.7264318,
            44.1237819
        ],
        "elevation": null,
        "type": "viewpoints",
        "source": "Viewpoints"
    },
    {
        "name": "No name",
        "coordinates": [
            -73.7539471,
            44.1431221
        ],
        "elevation": null,
        "type": "viewpoints",
        "source": "Viewpoints"
    },
    {
        "name": "No name",
        "coordinates": [
            -74.4313353,
            44.033521
        ],
        "elevation": null,
        "type": "viewpoints",
        "source": "Viewpoints"
    },
    {
        "name": "No name",
        "coordinates": [
            -73.9129418,
            44.3699871
        ],
        "elevation": null,
        "type": "viewpoints",
        "source": "Viewpoints"
    },
    {
        "name": "No name",
        "coordinates": [
            -73.9039826,
            44.3821461
        ],
        "elevation": null,
        "type": "viewpoints",
        "source": "Viewpoints"
    },
    {
        "name": "No name",
        "coordinates": [
            -73.7774306,
            44.3563551
        ],
        "elevation": null,
        "type": "viewpoints",
        "source": "Viewpoints"
    },
    {
        "name": "No name",
        "coordinates": [
            -73.7786884,
            44.3576289
        ],
        "elevation": null,
        "type": "viewpoints",
        "source": "Viewpoints"
    },
    {
        "name": "No name",
        "coordinates": [
            -73.7081994,
            44.2642764
        ],
        "elevation": null,
        "type": "viewpoints",
        "source": "Viewpoints"
    },
    {
        "name": "No name",
        "coordinates": [
            -73.7309795,
            44.2759785
        ],
        "elevation": null,
        "type": "viewpoints",
        "source": "Viewpoints"
    },
    {
        "name": "No name",
        "coordinates": [
            -73.7163806,
            44.2719373
        ],
        "elevation": null,
        "type": "viewpoints",
        "source": "Viewpoints"
    },
    {
        "name": "No name",
        "coordinates": [
            -73.7396772,
            44.2662085
        ],
        "elevation": null,
        "type": "viewpoints",
        "source": "Viewpoints"
    },
    {
        "name": "No name",
        "coordinates": [
            -73.7303785,
            44.2762596
        ],
        "elevation": null,
        "type": "viewpoints",
        "source": "Viewpoints"
    },
    {
        "name": "No name",
        "coordinates": [
            -73.7196671,
            44.273076
        ],
        "elevation": null,
        "type": "viewpoints",
        "source": "Viewpoints"
    },
    {
        "name": "No name",
        "coordinates": [
            -73.7389009,
            44.269241
        ],
        "elevation": null,
        "type": "viewpoints",
        "source": "Viewpoints"
    },
    {
        "name": "No name",
        "coordinates": [
            -73.8413099,
            44.3658923
        ],
        "elevation": null,
        "type": "viewpoints",
        "source": "Viewpoints"
    },
    {
        "name": "No name",
        "coordinates": [
            -73.8695559,
            44.3662096
        ],
        "elevation": null,
        "type": "viewpoints",
        "source": "Viewpoints"
    },
    {
        "name": "No name",
        "coordinates": [
            -73.8683004,
            44.3654702
        ],
        "elevation": null,
        "type": "viewpoints",
        "source": "Viewpoints"
    },
    {
        "name": "No name",
        "coordinates": [
            -73.8728362,
            44.3678416
        ],
        "elevation": null,
        "type": "viewpoints",
        "source": "Viewpoints"
    },
    {
        "name": "No name",
        "coordinates": [
            -73.8719071,
            44.3675471
        ],
        "elevation": null,
        "type": "viewpoints",
        "source": "Viewpoints"
    },
    {
        "name": "No name",
        "coordinates": [
            -73.7165977,
            44.2340052
        ],
        "elevation": null,
        "type": "viewpoints",
        "source": "Viewpoints"
    },
    {
        "name": "No name",
        "coordinates": [
            -74.4663138,
            44.2257572
        ],
        "elevation": null,
        "type": "viewpoints",
        "source": "Viewpoints"
    },
    {
        "name": "No name",
        "coordinates": [
            -73.51434,
            44.4015321
        ],
        "elevation": null,
        "type": "viewpoints",
        "source": "Viewpoints"
    },
    {
        "name": "No name",
        "coordinates": [
            -73.508943,
            44.3974499
        ],
        "elevation": null,
        "type": "viewpoints",
        "source": "Viewpoints"
    }
]